canonicalwebteam/__init__.py
canonicalwebteam/templatetags/__init__.py
canonicalwebteam/templatetags/versioned_static.py
canonicalwebteam.versioned_static-1.0.2.dist-info/DESCRIPTION.rst
canonicalwebteam.versioned_static-1.0.2.dist-info/METADATA
canonicalwebteam.versioned_static-1.0.2.dist-info/RECORD
canonicalwebteam.versioned_static-1.0.2.dist-info/WHEEL
canonicalwebteam.versioned_static-1.0.2.dist-info/metadata.json
canonicalwebteam.versioned_static-1.0.2.dist-info/top_level.txt
