Metadata-Version: 2.0
Name: canonicalwebteam.versioned-static
Version: 1.0.2
Summary: A Django template tag for generating a URL for a static file, with a version string which will be effectively unique based on the contents of the file.
Home-page: https://github.com/ubuntudesign/django-versioned-static-url
Author: Canonical webteam
Author-email: webteam+pypi@canonical.com
License: UNKNOWN
Platform: UNKNOWN
Requires-Dist: Django (>=1.3)
